Workbook

Sheet Dashboard
A1: Executive Opportunity Pipeline Dashboard
A3: Metric | B3: Value
A4: Total Organizations | B4: =COUNTA('Community Colleges '!A2:A640) -> 245
A5: High Priority Organizations | B5: =COUNTIF('Community Colleges '!AN2:AN640,"High") -> 0
A6: Follow-ups Due This Week | B6: =COUNTIFS('Community Colleges '!AL2:AL640,">="&TODAY(),'Community Colleges '!AL2:AL640,"<="&TODAY()+7)+COUNTIFS(Opportunities!M2:M500,">="&TODAY(),Opportunities!M2:M500,"<="&TODAY()+7) -> 1
A7: Overdue Follow-ups | B7: =COUNTIFS('Community Colleges '!AL2:AL640,"<>",'Community Colleges '!AL2:AL640,"<"&TODAY())+COUNTIFS(Opportunities!M2:M500,"<>",Opportunities!M2:M500,"<"&TODAY()) -> 0
A8: Active Opportunities | B8: =COUNTIFS(Opportunities!H2:H500,"<>Closed Won",Opportunities!H2:H500,"<>Closed Lost",Opportunities!A2:A500,"<>") -> 99
A9: Proposals Pending | B9: =COUNTIF(Proposals!G2:G500,"Pending Decision") -> 0
A10: Contracts Signed | B10: =COUNTIF(Opportunities!H2:H500,"Contract Signed") -> 0
A11: Revenue Won | B11: =SUMIFS(Revenue!E2:E500,Revenue!H2:H500,"Paid")+SUMIFS(Revenue!E2:E500,Revenue!H2:H500,"Partial Payment") -> 0
A12: Weighted Pipeline | B12: =SUM(Opportunities!G2:G500) -> 9000
A14: Pipeline Stage | B14: Count | C14: Weighted Value | D14: Notes
A15: Prospect Identified | B15: =COUNTIF(Opportunities!H:H,A15) -> 0 | C15: =SUMIF(Opportunities!H:H,A15,Opportunities!G:G) -> 0
A16: Research Complete | B16: =COUNTIF(Opportunities!H:H,A16) -> 1 | C16: =SUMIF(Opportunities!H:H,A16,Opportunities!G:G) -> 9000
A17: Executive Packet Sent | B17: =COUNTIF(Opportunities!H:H,A17) -> 0 | C17: =SUMIF(Opportunities!H:H,A17,Opportunities!G:G) -> 0
A18: Discovery Call Scheduled | B18: =COUNTIF(Opportunities!H:H,A18) -> 0 | C18: =SUMIF(Opportunities!H:H,A18,Opportunities!G:G) -> 0
A19: Discovery Call Completed | B19: =COUNTIF(Opportunities!H:H,A19) -> 0 | C19: =SUMIF(Opportunities!H:H,A19,Opportunities!G:G) -> 0
A20: Proposal Sent | B20: =COUNTIF(Opportunities!H:H,A20) -> 0 | C20: =SUMIF(Opportunities!H:H,A20,Opportunities!G:G) -> 0
A21: Negotiation | B21: =COUNTIF(Opportunities!H:H,A21) -> 0 | C21: =SUMIF(Opportunities!H:H,A21,Opportunities!G:G) -> 0
A22: Contract Signed | B22: =COUNTIF(Opportunities!H:H,A22) -> 0 | C22: =SUMIF(Opportunities!H:H,A22,Opportunities!G:G) -> 0
A23: Retreat/Engagement Scheduled | B23: =COUNTIF(Opportunities!H:H,A23) -> 0 | C23: =SUMIF(Opportunities!H:H,A23,Opportunities!G:G) -> 0
A24: Engagement Complete | B24: =COUNTIF(Opportunities!H:H,A24) -> 0 | C24: =SUMIF(Opportunities!H:H,A24,Opportunities!G:G) -> 0
A25: Follow-up Services | B25: =COUNTIF(Opportunities!H:H,A25) -> 0 | C25: =SUMIF(Opportunities!H:H,A25,Opportunities!G:G) -> 0
A26: Annual Advisory Relationship | B26: =COUNTIF(Opportunities!H:H,A26) -> 0 | C26: =SUMIF(Opportunities!H:H,A26,Opportunities!G:G) -> 0
... A28: Closed Lost | B28: =COUNTIF(Opportunities!H:H,A28) -> 0 | C28: =SUMIF(Opportunities!H:H,A28,Opportunities!G:G) -> 0

Sheet Community Colleges 
A1: Org ID | B1: Organization | C1: Institution Type | D1: District | E1: State | F1: Region | G1: Website | H1: Board Page | I1: Chancellor | J1: Chancellor Phone | K1: Chancellor Address | L1: Chancellor Email | M1: President/CEO | N1: Appointed | O1: Interim (Y/N) | P1: Primary Email | Q1: Board Chair | R1: Term Begin (C) | S1: Term End (C) | T1: Board Vice Chair | U1: Term Begin (VC) | V1: Term End (VC) | W1: Board email | X1: Primary Phone | Y1: Executive Assistant/Office Manager | Z1: Executive Assistant Email | AA1: Mailing Address | AB1: Strategic Priorities | AC1: Strategic Plan | AD1: Strategic Plan Years | AE1: President's Workplan | AF1: Current Initiatives | AG1: Accreditation Cycle | AH1: Recent News/Governance Notes | AI1: Date Identified | AJ1: Last Contact | AK1: Next Follow-up | AL1: Relationship Status | AM1: Priority | AN1: Fit Score | AO1: Packet Sent? | AP1: Notes | AQ1: Last Verified Date
A2: CC-001 | B2: Bates Technical College | C2: Community College | E2: Washington | F2: Pacific Northwest | G2: https://www.batestech.edu | H2: https://www.batestech.edu/about-bates/college-governance/ | M2: Dr. Lin Zhou | N2: 2018 | O2: N | P2: president@batestech.edu | Q2: Heather Moss | R2: 43132 | S2: n/a | T2: Florence Chang | U2: 43678 | W2: n/a | X2: 253-680-7100 | Y2: Hannah Herber | AA2: 1101 South Yakima Avenue Tacoma, WA 98405 | AB2: Workforce Education, Student Focus, Intentional Engagement | AC2: https://dms.batestech.edu/wp-content/uploads/documents-directory/strategic-plan/2024-29%20Strategic%20Plan%20Report_final.pdf | AD2: 2024-2029 | AE2: https://dms.batestech.edu/wp-content/uploads/documents-directory/offices/president/President_WorkPlan_FY2025-26(1).pdf | AF2: Strategic plan refresh; board retreat cycle | AG2: 2027 | AH2: Recent board priority discussion | AI2: 46205 | AJ2: 46205 | AK2: 46212 | AL2: Warm Prospect | AM2: High | AN2: 85 | AO2: No | AP2: Dr. Zhou is the college’s first female president, and the first female Chinese immigrant to serve as president at a public two-year college in Washington state. | AQ2: 46205
A3: CC-002 | B3: Bellevue College | C3: Community College | E3: Washington | F3: Pacific Northwest | G3: https://www.bellevuecollege.edu | H3: https://www.bellevuecollege.edu/about-us/college-leadership/board-trustees/ | M3: Dr. David May | N3: 2023 | O3: N | P3: david.may@bellevuecollege.edu | Q3: Pradnya Desh | S3: 46266 | T3: Rich Fukutaki | U3: 2015 | W3: pradnya.desh@bellevuecollege.edu | X3: 425.564.2303 | Y3: Amanda Morris | Z3: amanda.morris@bellevuecollege.edu | AA3: Bellevue College 3000 Landerholm Circle _x000B_SE MS A201 Bellevue, WA 98007-6406 | AC3: https://www.btc.edu/AboutBTC/ReportsandPolicies/InstitutionalEffectiveness.html#StrategicPlan | AD3: 2026-2031
A4: CC-003 | B4: Bellingham Technical College | E4: Washington | F4: Pacific Northwest | G4: https://www.btc.edu | H4: https://www.btc.edu/AboutBTC/OfficeofthePresident.html#BoardofTrustees | M4: Dr. James Lemerond | N4: 2023 | O4: N | P4: jlemerond@btc.edu | Q4: Robert DeCoteau | R4: 44986 | S4: n/a | T4: Alex Hildreth | U4: 45717 | W4: n/a | X4: 360.752.8334 | Z4: president@btc.edu | AA4: 3028 Lindbergh Ave, Bellingham, WA 98225 | AD4: 2023-2030 | AE4: https://www.btc.edu/AboutBTC/ReportsandPolicies/InstitutionalEffectiveness.html#StrategicPlan
A5: CC-004 | B5: Big Bend Community College | E5: Washington | F5: Pacific Northwest | G5: https://www.bigbend.edu | H5: https://www.bigbend.edu/about-us/board-of-trustees.html | M5: Dr. Sara Thompson Tweedy | N5: 2020 | O5: N | P5: SaraT@bigbend.edu | Q5: Amy Parris | R5: 44440 | S5: n/a | T5: Bethany Martinez | U5: 2022 | W5: n/a | X5: (509) 793-2000 | Y5: Chanda Rodriguez | Z5: ChandraR@bigbend.edu | AA5: 7662 Chanute St NE, Moses Lake, WA 98837 | AC5: https://www.bigbend.edu/_migrated-binaries/wp-content/uploads/Strategic-Plan-Most-Recent.pdf | AD5: 2021 - 2026
A6: CC-005 | B6: Cascadia College | E6: Washington | F6: Pacific Northwest | G6: https://www.cascadia.edu | H6: https://www.cascadia.edu/about/governance-accreditation/trustees.aspx | M6: Dr. Eric Murray | N6: 2010 | O6: N | P6: emurray@cascadia.edu | Q6: Dr. Meghan Quint | T6: Mr. Alex Lee | X6: (425) 352-8810 | Y6: Susan Thomas | Z6: sthomas@cascadia.edu | AA6: 18345 Campus Way NE Bothell, WA 98011 | AC6: https://www.cascadia.edu/_resources/documents/about/governance-accreditation/Strategic%20Plan%202024-25%20v1_Apr11.pdf | AD6: 2024-2025
A7: CC-006 | B7: Centralia College | E7: Washington | F7: Pacific Northwest | G7: https://www.centralia.edu | H7: https://www.centralia.edu/about/leadership/trustees.aspx | M7: Dr. Bob Mohrbacher | N7: 2016 | O7: N | P7: bob.mohrbacher@centralia.edu | Q7: Annalee Tobey | R7: 44682 | T7: Pretrina Mullins | U7: 44470 | X7: 360-623-8552 | Y7: Janet Reaume | Z7: janet.reaume@centralia.edu | AA7: 600 Centralia College Blvd., Centralia, WA 98531 | AC7: https://www.centralia.edu/about/leadership/institutional-research/docs/strategic-plan-one-pager.pdf
A8: CC-007 | B8: Clark College | E8: Washington | F8: Pacific Northwest | G8: https://www.clark.edu | H8: https://www.clark.edu/about/governance/leadership/board/ | M8: Dr. Karin Edwards | N8: 2020 | O8: N | P8: kedwards@clark.edu | Q8: Marilee Scarbrough | R8: 2023 | S8: 2027 | T8: Suzanne Donaldson | U8: 2023 | V8: 2028 | X8: (360) 992 - 2101 | Y8: Darcy Feider | Z8: dfeider@clark.edu | AA8: Office of the President 1933 Fort Vancouver Way, BRD101 Vancouver, WA 98663-3598 | AC8: https://www.clark.edu/about/governance/strategic_plan/strategic-plan.pdf | AD8: 2023-2028
A9: CC-008 | B9: Clover Park Technical College | E9: Washington | F9: Pacific Northwest | G9: https://www.cptc.edu | H9: https://www.cptc.edu/about/trustees | M9: Dr. Joyce Loveday | N9: 2016 | O9: N | P9: joyce.loveday@cptc.edu | Q9: Eli Taylor | R9: 43435 | T9: Adria Buchanan | U9: 45597 | W9: president@cptc.edu | X9: (253)589-5500 | Y9: Thomas Oliver | Z9: Thomas.Oliver@cptc.edu | AA9: Office of the President Park Technical College 4500 Steilacoom Blvd SWLakewood, WA 98499-4004 | AC9: https://www.cptc.edu/sites/default/files/2026-04/Strategic%20Plan%2023%20rev%2010-2-2023_0.pdf | AD9: 2023-2028
A10: CC-009 | B10: Columbia Basin College | E10: Washington | F10: Pacific Northwest | G10: https://www.columbiabasin.edu | H10: https://www.columbiabasin.edu/connect/about-cbc/our-leadership/board-of-trustees.html | M10: Dr. Rebekah Woods | N10: 2017 | O10: N | P10: rwoods@columbiabasin.edu | Q10: Ofelia Rivas de Bredt | R10: 44470 | S10: 46266 | T10: Kimberly Harper | U10: 44105 | V10: 47727 | W10: president@columbiabasin.edu | X10: 509-547-0511 | AA10: Office of the President 2600 N. 20th Ave. Pasco, WA 99301 | AC10: https://www.columbiabasin.edu/_documents/handbooks-guides-reports-plans/columbia-basin-college-strategic-plan-accessible.pdf | AD10: 2022-2025
A11: CC-010 | B11: Edmonds College | E11: Washington | F11: Pacific Northwest | G11: https://www.edmonds.edu | H11: Edmonds Board | M11: Amit Singh | N11: 2018 | O11: N | P11: amit.singh@edmonds.edu | Q11: Dr. Courtney Wooten | R11: 45017 | S11: 47727 | T11: Wally Webster II | U11: 45566 | V11: 47391 | X11: 425.640.1516 | AA11: Dr. Amit Singh, President Edmonds College 20000 68th Ave. W. Lynnwood, WA 98036 | AC11: Comprehensive Plan | AD11: 2025-2026 | AP11: https://edcfedt.wa.aft.org/news/faculty-concerns-regarding-president-singhs-interview-puget-sound-business-journal
A12: CC-011 | B12: Everett Community College | E12: Washington | F12: Pacific Northwest | G12: https://www.everettcc.edu | H12: https://www.everettcc.edu/about/governance/board-of-trustees/ | M12: Dr. Chemene Crawford | N12: 2023 | O12: N | P12: ccrawford@everettcc.edu | Q12: Kelly Shepherd | R12: 44470 | T12: Joe M. Davis II | U12: 45627 | X12: 425-388-9572 | Y12: Rita Belvill | Z12: rbelvill@everettcc.edu | AA12: 2000 Tower Street, Olympus Hall 200 Everett, WA 98201 | AC12: https://www.everettcc.edu/wp-content/uploads/2026/06/strategic-plan-adopted-121421-FINAL-1.pdf | AD12: 2022-2027
A13: CC-012 | B13: Grays Harbor College | E13: Washington | F13: Pacific Northwest | G13: https://www.ghc.edu | H13: https://www.ghc.edu/board-trustees | M13: Dr. Carli Schiffner | N13: 2023 | O13: N | P13: carli.schiffner@ghc.edu | Q13: Dr. Paula Akerlund | R13: 43282 | T13: Ms. Astrid Aveledo | U13: 43405 | X13: 360-538-4001 | Y13: Ja’Shonae Cooks | Z13: ja'shonae.cooks@ghc.edu | AA13: Grays Harbor College 1620 Edward P. Smith Drive Aberdeen, WA 98520 | AC13: https://www.ghc.edu/wp-content/uploads/2025/12/CollegePlan2019-2026.pdf | AD13: 2019 - 2026
A14: CC-013 | B14: Green River College | E14: Washington | F14: Pacific Northwest | G14: https://www.greenriver.edu | H14: https://www.greenriver.edu/campus/board-of-trustees/index.html | M14: George Frasier, Interim President | N14: 2026 | O14: Y | P14: gfrasier@greenriver.edu | Q14: Sharonne Navas | R14: 42430 | T14: Jackie Boschok | U14: 42644 | Y14: Suzanne McCudden | Z14: smccudden@greenriver.edu | AA14: Green River College 12401 SE 320th Street Auburn, WA 98092-3622 | AC14: https://www.greenriver.edu/campus/media/documents/strategic-planning/Green_River_College-Equity_minded-Strategic_Plan.pdf | AD14: 2021 - 2026 | AP14: Board Goals dated - 2023-2024 Statement and Goals
A15: CC-014 | B15: Highline College | E15: Washington | F15: Pacific Northwest | G15: https://www.highline.edu | H15: https://trustees.highline.edu/members/ | M15: Dr. Jamilyn Penn, Interim President | N15: 2025 | O15: Y | P15: jpenn@highline.edu | Q15: Sharmila Swenson | R15: 43739 | T15: Joseph S. Bowman IV | U15: 44105 | X15: (206) 592-4943 | Y15: Juli Hammond | Z15: jhammond@highline.edu | AA15: Highline College P.O. Box 98000 M/S B12 Des Moines, WA 98198-9800
A16: CC-015 | B16: Lake Washington Institute of Technology | E16: Washington | F16: Pacific Northwest | G16: https://www.lwtech.edu | H16: https://www.lwtech.edu/about-us/trustees/index.aspx | M16: Dr. Amy Morrison | N16: 2013 | O16: N | P16: Amy.Morrison@lwtech.edu | X16: (425) 739-8202 | Y16: Hanna Charrette | Z16: Hanna.Charrette@lwtech.edu | AA16: 11605 132nd Avenue NE Kirkland, WA 98034 | AC16: LWTech Strategic Plan 2024-2029 | Lake Washington Institute of Technology | AD16: 2024-2029
A17: CC-016 | B17: Lower Columbia College | E17: Washington | F17: Pacific Northwest | G17: https://www.lowercolumbia.edu | H17: https://lowercolumbia.edu/trustees/ | M17: Dr. Kristen Finnel, Interim President | N17: 2026 | O17: Y | P17: kfinnel@lowercolumbia.edu | X17: (360) 442-2100 | Y17: Tracy Powell | Z17: tpowell@lowercolumbia.edu | AA17: Administration Building 1600 Maple Street, Longview, WA 98632 | AB17: https://northseattle.edu/media/document/3901 | AC17: https://lowercolumbia.edu/publications/strategic-plan/ | AD17: 2026-2027
A18: CC-017 | B18: North Seattle College | C18: Community College District | E18: Washington | F18: Pacific Northwest | G18: https://northseattle.edu | H18: https://www.seattlecolleges.edu/about/leadership-and-organization/board-trustees | I18: Dr Rosie Rimando-Chareunsap (2023) | J18: 206.934.4100 | K18: Seattle Colleges Siegel Administrative Center - Chancellor's Office 1500 Harvard Avenue Seattle, WA 98122 | L18: Rosie.Rimando@seattlecolleges.edu | M18: Dr. Rachel Solemsaas | N18: 2024 | O18: N | P18: Rachel.Solemsaas@seattlecolleges.edu | X18: (206) 934-7788 | Y18: Tony Stankovic | Z18: Toni.Stankovic@seattlecolleges.edu | AA18: 9600 College Way North Seattle, WA 98103 | AC18: https://www.seattlecolleges.edu/sites/seattlecolleges.southseattle.edu/files/2024-12/24%20Strategic%20Plan.vf_.pdf | AD18: 2024-2034
A19: CC-018 | B19: Olympic College | E19: Washington | F19: Pacific Northwest | G19: https://www.olympic.edu | H19: https://www.olympic.edu/about/board-trustees | M19: Dr. Chantae Recasner | N19: 2024 | O19: N | P19: crecasner@olympic.edu | X19: 360-475-7105 | Y19: Richard Barley | Z19: rbarley@olympic.edu | AA19: 1600 Chester Ave. Bremerton, WA 98337-1699 | AC19: https://www.olympic.edu/about/strategic-plan-2024-2028 | AD19: 2024-2028
A20: CC-019 | B20: Peninsula College | E20: Washington | F20: Pacific Northwest | G20: https://pencol.edu | H20: https://pencol.edu/about/board | M20: Dr. Suzy Ames | N20: 2022 | O20: N | P20: sames@pencol.edu | X20: (360) 417-6201 | Y20: Trisha Haggerty | Z20: thaggerty@pencol.edu | AA20: President’s OfficePeninsula College1502 E. Lauridsen BoulevardPort Angeles, WA 98362 | AC20: https://pencol.edu/sites/default/files/2020-2025-StrategicPlan.pdf | AD20: 2020-2025
A21: CC-020 | B21: Pierce College Fort Steilacoom | C21: Community College District | E21: Washington | F21: Pacific Northwest | G21: https://www.pierce.ctc.edu | H21: https://www.pierce.ctc.edu/about/mission-vision/board/index.html | I21: Dr. Julie A. White | J21: (253) 864-3100 | K21: Pierce College District9401 Farwest Drive SW | L21: JUWhite@pierce.ctc.edu | M21: Dr. Matthew Campbell | N21: 2023 | O21: N | P21: MCampbell@pierce.ctc.edu | X21: 253-964-6776 | Y21: Christine Boiter | Z21: CBoiter@pierce.ctc.edu | AA21: 9401 Farwest Drive SW, Lakewood, Washington 98498 | AC21: https://www.pierce.ctc.edu/documents/2025/08/25-32-StrategicPlan.pdf | AD21: 2025-2032
A22: CC-021 | B22: Pierce College Puyallup | C22: Community College District | E22: Washington | F22: Pacific Northwest | G22: https://www.pierce.ctc.edu | H22: https://www.pierce.ctc.edu/about/mission-vision/board/index.html | I22: Dr. Julie A. White | J22: (253) 864-3100 | K22: Pierce College District9401 Farwest Drive SW | L22: JUWhite@pierce.ctc.edu | M22: Dr. Chio Flores | N22: 2023 | O22: N | P22: CFlores@pierce.ctc.edu | X22: 253-840-8421 | Y22: Emily Donnelly | Z22: EDonnelly@pierce.ctc.edu | AA22: 1601 39th Avenue Southeast Puyallup, WA USA 98374 | AC22: https://www.pierce.ctc.edu/documents/2025/08/25-32-StrategicPlan.pdf | AD22: 2025-2032
A23: CC-022 | B23: Renton Technical College | E23: Washington | F23: Pacific Northwest | G23: https://rtc.edu | H23: https://rtc.edu/about-rtc/office-of-the-president/board.php | M23: Dr. Yoshiko Harden | N23: 2022 | O23: N | P23: yharden@rtc.edu | X23: (425) 235-2235 | Y23: Jordan Mellott Porter | Z23: jmellott@rtc.edu | AA23: Renton Technical College Office of the President 3000 NE 4th Street Renton, WA 98056 | AC23: https://rtc.edu/_resources/documents/20250812r-combined-SEP-indicators.pdf | AD23: 2024-2029 | AP23: Dr. Yoshiko Harden is the first woman and person of color to serve as President of RTC
A24: CC-023 | B24: Seattle Central College | E24: Washington | F24: Pacific Northwest | G24: https://seattlecentral.edu | H24: https://www.seattlecolleges.edu/about/leadership-and-organization/board-trustees | I24: Dr Rosie Rimando-Chareunsap (2023) | J24: 206.934.4100 | K24: Seattle Colleges Siegel Administrative Center - Chancellor's Office 1500 Harvard Avenue Seattle, WA 98122 | L24: Rosie.Rimando@seattlecolleges.edu | M24: Brent Jones, Interim President | N24: 2026 | O24: Y | P24: Brent.Jones@seattlecolleges.edu | X24: (206) 934-3034 | AA24: Office of the President Seattle Central College 1701 Broadway Seattle, WA 98122 | AC24: https://www.seattlecolleges.edu/sites/seattlecolleges.southseattle.edu/files/2024-12/24%20Strategic%20Plan.vf_.pdf | AD24: 2024-2034
A25: CC-024 | B25: Shoreline College | E25: Washington | F25: Pacific Northwest | G25: https://www.shoreline.edu | H25: https://www.shoreline.edu/about-shoreline/board/ | M25: Dr. Jack Kahn | N25: 2022 | O25: N | P25: jkahn@shoreline.edu | X25: (206) 546-4552 | Y25: Lori Yonemitsu | Z25: lyonemitsu@shoreline.edu | AC25: https://www.shoreline.edu/about-shoreline/documents/ShorelineCoCollege_EquityCenteredStratPlan2024_022924%20v6%20SPREADS.pdf | AD25: 2024-2029 | AP25: Board Goals dated - 2024-2025
A26: CC-025 | B26: Skagit Valley College | E26: Washington | F26: Pacific Northwest | G26: https://www.skagit.edu | H26: https://www.skagit.edu/leadership/trustees/ | M26: Dr. Thomas Keegan, Interim President | N26: 2026 | O26: Y | P26: Thomas.Keegan@skagit.edu | X26: 360.416.7995 | Y26: Pam Davis | Z26: pam.davis@skagit.edu | AA26: 2405 E. College Way, Mount Vernon, WA 98273 | AC26: https://www.skagit.edu/institutional-planning-student-success/accreditation/assets/25-26-261%20strategic-plan-v4.pdf | AD26: 2024-2028
A27: CC-026 | B27: South Puget Sound Community College | E27: Washington | F27: Pacific Northwest | G27: https://spscc.edu | M27: Timothy Stokes | N27: 2012 | O27: N | P27: tstokes@spscc.edu | X27: (360) 596-5498 | Y27: Diana Toledo | Z27: dtoledo@spscc.edu | AA27: 2011 Mottman Road SW Olympia, WA 98512 | AC27: https://spscc.edu/sites/default/files/2025-05/FINAL_Foundation_Strategic_0.pdf | AD27: 2024-2029 | AP27: Trustee emails are in the directory
A28: CC-027 | B28: South Seattle College | E28: Washington | F28: Pacific Northwest | G28: https://southseattle.edu | H28: https://www.seattlecolleges.edu/about/leadership-and-organization/board-trustees | I28: Dr Rosie Rimando-Chareunsap (2023) | J28: 206.934.4100 | K28: Seattle Colleges Siegel Administrative Center - Chancellor's Office 1500 Harvard Avenue Seattle, WA 98122 | L28: Rosie.Rimando@seattlecolleges.edu | M28: Dr. Monica Brown | N28: 2024 | O28: N | P28: Monica.Brown@seattlecolleges.edu | X28: (206) 934-6870 EA: 206/934-5312 | Y28: Koh Phasomsap | Z28: Koh.Phasomsap@seattlecolleges.edu | AA28: President South Seattle College Mailstop: RSB024 6000 16th Ave SW Seattle, WA 98106-1499 | AC28: https://www.seattlecolleges.edu/sites/seattlecolleges.southseattle.edu/files/2024-12/24%20Strategic%20Plan.vf_.pdf | AD28: 2024-2034
A29: CC-028 | B29: Spokane Community College | C29: Community College District | E29: Washington | F29: Pacific Northwest | G29: https://scc.spokane.edu | H29: https://ccs.spokane.edu/About-Us/Leadership/Board-of-Trustees | I29: Dr. Kevin Brockbank | J29: 509-434-5006 | K29: 501 N Riverpoint Blvd, MS1001 Spokane, WA 99202-1659 | L29: Kevin.Brockbank@ccs.spokane.edu | M29: Dr. Jenni Martin | N29: 2024 | O29: N | P29: Jenni.Martin@scc.spokane.edu | X29: 509-533-7042 | Y29: Nancy Delgado | Z29: nancy.delgado@scc.spokane.edu | AA29: 1810 North Greene Street, MS2150 Spokane, WA 99217-5320 | AC29: https://shared.spokane.edu/ccsglobal/media/Global/PDFs/District/Strategic%20Plan/21-212_StrategicPlan_accessible.pdf | AD29: 2021-2025 | AP29: Employee Success and Excellence is listed as a priority in the strategic plan
A30: CC-029 | B30: Spokane Falls Community College | C30: Community College District | E30: Washington | F30: Pacific Northwest | G30: https://sfcc.spokane.edu | H30: https://ccs.spokane.edu/About-Us/Leadership/Board-of-Trustees | I30: Dr. Kevin Brockbank | J30: 509-434-5006 | K30: 501 N Riverpoint Blvd, MS1001 Spokane, WA 99202-1659 | L30: Kevin.Brockbank@ccs.spokane.edu | M30: Patrick McEachern, Interim President | O30: Y | P30: Patrick.McEachern@sfcc.spokane.edu | X30: 509-533-3514 | Y30: Megan Gibson | Z30: megan.gibson@sfcc.spokane.edu | AA30: 3410 W Whistalks Way, MS3010 Spokane, WA 99224-5204 | AC30: https://shared.spokane.edu/ccsglobal/media/Global/PDFs/District/Strategic%20Plan/21-212_StrategicPlan_accessible.pdf | AD30: 2021-2025
A31: CC-030 | B31: Tacoma Community College | E31: Washington | F31: Pacific Northwest | G31: https://www.tacomacc.edu | H31: https://www.tacomacc.edu/about/leadership/trustees | M31: Dr. Ivan Harrell | N31: 2018 | O31: N | P31: iharrell@tacomacc.edu | X31: 253-566-5169 | Y31: Natalie Boes | Z31: nboes@tacomacc.edu | AA31: Tacoma Community College 6501 S 19th St Tacoma, WA 98466 | AC31: https://www.tacomacc.edu/about/strategicplan/strategicplan | AD31: 2026-2031
A32: CC-031 | B32: Walla Walla Community College | E32: Washington | F32: Pacific Northwest | G32: https://www.wwcc.edu | H32: https://www.wwcc.edu/about/leadership/board-of-trustees/ | M32: Dr. Chad Hickox | N32: 2020 | O32: N | P32: chad.hickox@wwcc.edu | X32: 509.527.4274 | Y32: Doreen Kennedy | Z32: doreen.kennedy@wwcc.edu | AA32: President’s Office Information Walla Walla Campus Administration (D) Bldg, Rm 61 | AC32: https://www.wwcc.edu/about/mission-vision-and-planning/institutional-planning/ | AD32: 2023-2028
A33: CC-032 | B33: Wenatchee Valley College | E33: Washington | F33: Pacific Northwest | G33: https://www.wvc.edu | H33: https://wvc.edu/about/leadership/board-of-trustees/index.html | M33: Dr. Faimous Harrison | N33: 2023 | O33: N | P33: fharrison@wvc.edu | X33: 509.682.6400 | Y33: Maria Iñiguez | Z33: miniguez@wvc.edu | AA33: President's Office Wenatchee Valley College 1300 Fifth St. Wenatchee, WA 98801 | AC33: https://wvc.edu/about/about-wvc/institutional-effectiveness/strategicplanning/index.html | AD33: 2024-2030
A34: CC-033 | B34: Whatcom Community College | C34: Community College | E34: Washington | F34: Pacific Northwest | G34: https://www.whatcom.edu | H34: https://www.whatcom.edu/about-wcc/college-leadership/board-of-trustees | M34: Dr. Justin Guillory | N34: 2025 | O34: N | P34: jguillory@whtacom.edu | X34: 360.383.3338 | Y34: Rafeeka Kloke | Z34: rkloke@whatcom.edu | AA34: Office of the President Whatcom Community College 237 W. Kellogg Road Bellingham, WA 98226 | AC34: https://www.whatcom.edu/about-wcc/about-the-college/mission-strategic-plan | AD34: 2023-2028
A35: CC-034 | B35: Yakima Valley College | C35: Community College | E35: Washington | F35: Pacific Northwest | G35: https://www.yvcc.edu | H35: https://yvcc.edu/board-of-trustees.php | M35: Dr. Teresa Rich | N35: 2026 | O35: N | P35: teresarich@yvcc.edu | X35: 509-574-4635 | Y35: Jocelyn Sheehan | Z35: jsheehan@yvcc.edu | AA35: P.O. Box 22520 Yakima, WA 98907-2520 | AC35: https://yvcc.edu/presidents-office/strategic-plan.php | AD35: 2021-2026
A36: CC-035 | B36: Allan Hancock College | C36: Community College | E36: California | F36: Pacific | G36: https://www.hancockcollege.edu | H36: https://www.hancockcollege.edu/board/index.php | M36: Dr. Kevin G. Walthers | N36: 2014 | O36: N | P36: kevin.walthers@hancockcollege.edu | X36: 805-922-6966 ext. 3245 | Y36: Janet McGee | Z36: jmcgee@hancockcollege.edu | AA36: Office of the President Allan Hancock College 1300 S. College Drive Santa Maria, CA 934 | AC36: https://www.hancockcollege.edu/planning/index.php | AP36: Podcast - Hancock Conversations; unable to find and actual strategic planning document
A37: CC-036 | B37: American River College | C37: Community College District | D37: Los Rios Community College District | E37: California | F37: Pacific | G37: https://arc.losrios.edu | H37: https://losrios.edu/about-los-rios/board-of-trustees | I37: Dr. Torence Powell (2026) | J37: (916) 568-3021 | K37: Los Rios Community College District1919 Spanos CourtSacramento, CA 95825-3981 | L37: powellt@losrios.edu | M37: Dr. Lisa Cardoza | N37: 2023 | O37: N | P37: cardozal@arc.losrios.edu | X37: (916) 484-8011 | Y37: Amanda Lewis | Z37: lewisa@arc.losrios.edu | AA37: 4700 College Oak Drive, Sacramento, CA 95841 | AC37: https://losrios.edu/about-los-rios/our-values/strategic-plan | AD37: 2016-2021 | AP37: Lisa Cardoza serves as the first Latina President of American River College, the largest college in the Los Rios Community College District
A38: CC-037 | B38: Antelope Valley College | C38: Community College District | E38: California | F38: Pacific | G38: https://www.avc.edu | H38: https://www.avc.edu/board-trustees | M38: Dr. Jennifer Zellet | N38: 2022 | O38: N | P38: jennifer.zellet@avc.edu | X38: (661) 722-6300, ext. 6301 | Y38: Michele Schottelkorb | Z38: michele.schottelkorb@avc.edu | AA38: Superintendent/President Antelope Valley College 3041 West Avenue K Lancaster, CA 93536-5426 | AE38: Superintendent/President Goals for 2025-2026
A39: CC-038 | B39: Bakersfield College | C39: Community College District | D39: Kern Community College District | E39: California | F39: Pacific | G39: https://www.bakersfieldcollege.edu | H39: https://www.kccd.edu/board-trustees/index.html | I39: Dr. Steven Bloomberg | J39: (661) 336-5104 | K39: 2100 Chester AvenueBakersfield, CA 93301 | L39: steven.bloomberg@kccd.edu | M39: Dr. Stacy Pfluger | N39: 2026 | O39: N | P39: stacy.pfluger@bakersfieldcollege.edu | X39: (661) 395-4211 | Y39: Catherine Guerrero | Z39: catherine.guerrero@bakersfieldcollege.edu | AA39: Bakersfield CollegeAttn: Office of the President1801 Panorama DriveBakersfield, CA 93305-1219 | AC39: https://www.kccd.edu/chancellors-office/_documents/strategic-plan/kccd-strategic-plan-june-2025-bot.pdf | AD39: 2025-2030 | AP39: Kern Community College District
A40: CC-039 | B40: Barstow Community College | E40: California | F40: Pacific | G40: https://www.barstow.edu | H40: https://www.barstow.edu/about-bcc/board-trustees | M40: Dr. Eva Bagg | N40: 2017 | O40: N | P40: ebagg@barstow.edu | X40: (760) 252-2411, ext. 7214 | Y40: Michelle Henderson | Z40: mhenderson@barstow.edu | AA40: 2700 Barstow Road, Barstow, CA 92311 | AC40: https://www.barstow.edu/about-bcc/institutional-effectiveness/strategic-plan | AP40: Board Goals 2026-2028
A41: CC-040 | B41: Berkeley City College | C41: Community College District | D41: Peralta Community College District | E41: California | F41: Pacific | G41: https://www.berkeleycitycollege.edu | H41: https://www.peralta.edu/boardoftrustees | I41: Dr. Tammeil Gilkerson | J41: 510/466-7322 | K41: Peralta Community College District 333 East Eighth Street Oakland, CA 94606 | L41: tgilkerson@peralta.edu | M41: Dr. Denise Richardson | N41: 2023 | O41: N | P41: drichardson@peralta.edu | X41: (510) 981-2800 | Y41: Annie Liu | Z41: aliu@peralta.edu | AA41: Office of the President Berkeley City College 2050 Center Street Berkeley, California 94704 | AC41: https://www.berkeleycitycollege.edu/hubfs/Berkeley%20City%20College%202023-28%20Strategic%20Plan.pdf | AD41: 2023-2028 | AP41: Peralta Community College District
A42: CC-041 | B42: Butte College | E42: California | F42: Pacific | G42: https://www.butte.edu | H42: https://www.butte.edu/about/leadership/board-of-trustees/index.html | M42: Virginia L. Guleff | N42: 2022 | O42: N | P42: guleffvi@butte.edu | X42: (530) 895-2484 | Y42: Melissa Cafferata-Ainsworth | Z42: cafferataainsworthme@butte.edu | AA42: President's OfficeButte College3536 Butte Campus DriveOroville, CA 95965 | AC42: https://www.butte.edu/about/leadership/planning-documents/_documents/2024-27strategicplan.pdf | AD42: 2024-2027
A43: CC-042 | B43: Cabrillo College | E43: California | F43: Pacific | G43: https://www.cabrillo.edu | H43: https://www.cabrillo.edu/about-cabrillo/#board-of-trustees | M43: Dr. Jenn Capps | N43: 2026 | O43: N | P43: jenn.capps@cabrillo.edu | X43: (831) 479-6302 | Y43: Ronnette Smithcamp | Z43: rosmithc@cabrillo.edu | AA43: Cabrillo Community College District6500 Soquel DriveAptos, CA 95003-3198 | AC43: https://www.cabrillo.edu/2030/ | AD43: IN PROGRESS
A44: CC-043 | B44: Calbright College | E44: California | F44: Pacific | G44: https://www.calbright.org | H44: https://www.calbright.edu/about/board/ | M44: Ajita Talwalker Menon | N44: 2020 | O44: N | P44: ajita@calbright.org | Y44: Carmen Drummond | Z44: carmen@calbright.org | AA44: 1102 Q Street, Suite 4800, Sacramento, CA 95811 | AC44: https://www.calbright.edu/wp-content/uploads/2024/01/Calbright-College-Strategic-Vision-2024-2027.pdf | AD44: 2024-2027
A45: CC-044 | B45: Cañada College | C45: Community College District | E45: California | F45: Pacific | G45: https://www.canadacollege.edu | H45: https://smccd.edu/boardoftrustees/members.php | I45: Melissa Moreno | J45: (650) 358-6885 | K45: District Office 3401 CSM Drive San Mateo, CA 94402. | L45: morenomelissa@smccd.edu | M45: Kim Lopez | N45: 2021 | O45: N | P45: lopezk@smccd.edu | X45: (650) 306-3456 | Z45: canexasst@smccd.edu | AA45: 4200 Farm Hill Boulevard, Redwood City, CA 94061 | AC45: https://smccd.edu/strategicplanning/Updated_2025_DistrictStrategicPlan_11x8.5in.pdf | AD45: 2025-2030
A46: CC-045 | B46: Cerritos College | E46: California | F46: Pacific | G46: https://www.cerritos.edu | H46: https://www.cerritos.edu/about/board/default.htm | M46: Dr. José Fierro | N46: 2015 | O46: N | P46: jfierro@cerritos.edu. | X46: (562) 860-2451 ext 2204 | Y46: Andrea Wittig | Z46: awittig@cerritos.edu | AA46: Cerritos College11110 Alondra Blvd.Norwalk, CA 90650
A47: CC-046 | B47: Cerro Coso Community College | C47: Community College District | D47: Kern Community College District | E47: California | F47: Pacific | G47: https://www.cerrocoso.edu | H47: https://www.kccd.edu/board-trustees/index.html | I47: Steven Bloomberg | J47: (661) 336-5104 | K47: 2100 Chester AvenueBakersfield, CA 93301 | L47: steven.bloomberg@kccd.edu | M47: Dr. Sean Hancock | N47: 2026 | O47: N | P47: sean.hancock@cerrocoso.edu | X47: (760) 384-6212 | Y47: Jennifer Curtis | Z47: jennifer.curtis@cerrocoso.edu | AA47: Cerro Coso Community College3000 College Heights Blvd.Ridgecrest, CA 93555 | AC47: https://www.cerrocoso.edu/_resources/assets/documents/About/Strategic-Plan-2025-2030-Brochure.pdf | AD47: 2025-2030
A48: CC-047 | B48: Chabot College | E48: California | F48: Pacific | G48: https://www.chabotcollege.edu | H48: https://www.clpccd.org/bot/index.php | I48: Ronald P. Gerhard | J48: (925) 485-5206 | K48: Chabot-Las Positas Community College District7600 Dublin Blvd, 3rd FloorDublin, CA 94568 | L48: rgerhard@clpccd.org | M48: Dr. Jamal Cooks | N48: 2023 | O48: N | P48: jcooks@chabotcollege.edu | X48: 510.723.6641 | Y48: Kirti Reddy | Z48: kreddy@chabotcollege.edu | AA48: Chabot College25555 Hesperian BoulevardHayward, CA 94545
A49: CC-048 | B49: Chaffey College | E49: California | F49: Pacific | G49: https://www.chaffey.edu | H49: https://www.chaffey.edu/leadership/governingboard.php | M49: Dr. Henry Shannon | N49: 2007 | O49: N | P49: henry.shannon@chaffey.edu | X49: (909) 652-6101 | Y49: Eva Ramirez | Z49: Eva.Ramirez@chaffey.edu | AA49: Office of the Superintendent/PresidentChaffey College5885 Haven AvenueRancho Cucamonga, CA 91737-3002 | AC49: https://www.chaffey.edu/about/accreditation/docs/strategic_plans_chaffey_college_23-26.pdf | AD49: 2023-2026
A50: CC-049 | B50: Citrus College | E50: California | F50: Pacific | G50: https://www.citruscollege.edu | H50: https://www.citruscollege.edu/admin/bot/index.html | M50: Dr. Greg Schulz | N50: 2021 | O50: N | P50: gschulz@citruscollege.edu | X50: (626) 914-8821 | Y50: Cydney Leon | Z50: cleon@citruscollege.edu | AA50: Citrus College, 1000 West Foothill Boulevard, Glendora, CA 91741-1899 | AC50: https://files.citruscollege.edu/research/planning/sp2631ada.pdf | AD50: 2026-2031
A51: CC-050 | B51: City College of San Francisco | E51: California | F51: Pacific | G51: https://www.ccsf.edu | H51: https://www.ccsf.edu/about-ccsf/board-trustees | M51: Dr. Kimberlee Messina Ed.D | N51: 2025 | O51: N | P51: kmessina@ccsf.edu | X51: 415-239-3556 | Y51: Mary Grace Esteban | Z51: mesteban@ccsf.edu | AA51: Office of the ChancellorCity College of San Francisco50 Phelan Ave, Box E-200San Francisco, CA 94112
A52: CC-051 | B52: Clovis Community College | D52: State Center Community College District | E52: California | F52: Pacific | G52: https://www.cloviscollege.edu | H52: https://www.scccd.edu/about/board-of-trustees/index.html | I52: Dr. Carole Goldsmith | J52: (559) 243-7100 ext 7102 | K52: Chancellor's Office State Center Community College District1171 Fulton Street Fresno, CA 93721 | L52: RETIRING - SEARCH IN PROGRESS | M52: Dr. Kim E. Armstrong | N52: 2023 | O52: N | P52: kim.armstrong@cloviscollege.edu | X52: (559) 325-5205 | AA52: Clovis Community College 10309 North Willow Avenue Fresno, CA 93730 | AC52: https://www.cloviscollege.edu/_uploaded-files/_documents/about/planning/ccc-strategic-plan-2025-2029.pdf | AD52: 2025-2029
A53: CC-052 | B53: Coalinga College | C53: Community College District | D53: West Hills Community College District | E53: California | F53: Pacific | G53: https://www.westhillscollege.com/coalinga | H53: https://westhillscollege.com/district/administration/board-of-trustees/ | I53: Dr. Robert Pimentel | J53: (559) 934-2131 | K53: West Hills Community College District 275 Phelps Ave Coalinga, CA 93210 | L53: robertpimentel@whccd.edu | M53: Dr. Carla Tweed | N53: 2022 | O53: N | P53: carlatweed@whccd.edu | X53: (559) 934-2205 | AA53: President Coalinga College 300 Cherry Lane Coalinga, CA 93210 | AC53: https://issuu.com/westhillsmagazine/docs/64506727_whcc_strategic_plan_2021-2026?mode=window | AD53: 2021-2026
A54: CC-053 | B54: Coastline College | C54: Community College District | D54: Coast Community College District | E54: California | F54: Pacific | G54: https://www.coastline.edu | H54: https://www.cccd.edu/boardoftrustees/index.html | I54: Dr. Whitney Yamamura | J54: (714)438-4732 | K54: 1370 Adams Avenue Costa Mesa, CA 92626 | L54: wyamamura@cccd.edu | M54: Dr. Vince Rodriguez | N54: 2021 | O54: N | P54: vrodriguez@coastline.edu | Y54: Patty Gilyeart | Z54: pfranco@coastline.edu | AA54: President, Coastline College11460 Warner AvenueFountain Valley, CA 92708-2597 | AC54: https://documents.coastline.edu/research%20and%20planning/__CollegePlans/Coastline%20College%202030%20Vision%20Plan.pdf
A55: CC-054 | B55: College of Alameda | D55: Peralta Community College District | E55: California | F55: Pacific | G55: https://www.alameda.edu | H55: https://www.peralta.edu/boardoftrustees | I55: Dr. Tammeil Gilkerson | J55: 510/466-7322 | K55: Peralta Community College District 333 East Eighth Street Oakland, CA 94606 | L55: tgilkerson@peralta.edu | M55: Melanie Dixon | N55: 2024 | O55: N | P55: melaniedixon@peralta.edu | X55: 510-748-2273 | Y55: Nickey Heredia | Z55: NHEREDIA@peralta.edu | AA55: College of Alameda555 Ralph Appezzato Memorial ParkwayAlameda, CA 94501
A56: CC-055 | B56: College of Marin | E56: California | F56: Pacific | G56: https://www.marin.edu | H56: https://www1.marin.edu/board-trustees | M56: Dr. Jonathan Eldridge | N56: 2024 | O56: N | P56: JEldridge@marin.edu | X56: 628-234-7400 | AA56: College of Marin835 College AvenueKentfield, CA 94904 | AC56: https://prie.marin.edu/sites/default/files/Strategic-Plan-2022-2025-e.pdf | AD56: 2022-2025
A57: CC-056 | B57: College of San Mateo | C57: Community College District | E57: California | F57: Pacific | G57: https://collegeofsanmateo.edu | H57: https://smccd.edu/boardoftrustees/members.php | I57: Melissa Moreno | J57: (650) 358-6885 | K57: District Office 3401 CSM Drive San Mateo, CA 94402. | L57: morenomelissa@smccd.edu | M57: Manuel Alejandro Perez | N57: 2024 | O57: N | P57: perezma@smccd.edu | X57: 650) 574-6222 | Y57: Anjelica Soria Mendoza | Z57: mendozaa@smccd.edu | AA57: College of San Mateo President's Office BLDG 10-490, 1700 West Hillsdale Blvd San Mateo, CA 94402 | AC57: https://smccd.edu/strategicplanning/Updated_2025_DistrictStrategicPlan_11x8.5in.pdf | AD57: 2025-2030
A58: CC-057 | B58: College of the Canyons | E58: California | F58: Pacific | G58: https://www.canyons.edu | H58: https://www.canyons.edu/administration/board/ | M58: Dr. Jasmine Ruys | N58: 2026 | O58: N | P58: Jasmine.Ruys@canyons.edu | X58: (661) 362-3280 | Y58: Kristina Hancock | Z58: kristina.hancock-nishimoto@canyons.edu | AA58: College of the Canyons26455 Rockwell Canyon RoadSanta Clarita, CA 91355 | AC58: https://www.canyons.edu/_documents/administration/pio/2023-26-Strategic-Plan-rev011824-508.pdf | AD58: 2023-2026
A59: CC-058 | B59: College of the Desert | E59: California | F59: Pacific | G59: https://www.collegeofthedesert.edu | H59: https://www.collegeofthedesert.edu/community/board-of-trustees/default.php | M59: Val Martinez Garcia | N59: 2025 | O59: N | P59: vmartinezgarcia@collegeofthedesert.edu | X59: 760.346.8041 ext 7270 | Y59: Marbella Ordaz | Z59: maordaz@collegeofthedesert.edu | AA59: Superintendent/President's Office College of the Desert 43-500 Monterey Avenue Palm Desert, CA 92260
A60: CC-059 | B60: College of the Redwoods | E60: California | F60: Pacific | G60: https://www.redwoods.edu | H60: https://www.redwoods.edu/about/board/index.php | M60: Dr. Keith Flamer | N60: 2015 | O60: N | P60: keith-flamer@redwoods.edu | X60: (707) 476-4170 | Y60: Julie Gilbride | Z60: julie-gilbride@redwoods.edu | AA60: College of the Redwoods7351 Tompkins Hill RoadEureka, CA 95501 | AP60: National presidential search underway; Dr. Flamer retiring at the end of 2026
A61: CC-060 | B61: College of the Sequoias | E61: California | F61: Pacific | G61: https://www.cos.edu | H61: https://www.cos.edu/en-us/administration/governance/board | M61: Dr. Brent Calvin | N61: 2018 | O61: N | P61: brentc@cos.edu | X61: (559) 730-3745 | Y61: Kinetha Cochran | Z61: kinethac@cos.edu | AA61: College of the Sequoias 915 S. Mooney Boulevard Visalia, CA 93277 | AC61: https://www.cos.edu/en-us/Accreditation/Documents/Institutional%20Planning%20Documents/2025_2028%20Strategic%20Plan.pdf | AD61: 2025-2028
A62: CC-061 | B62: College of the Siskiyous | C62: Community College | E62: California | F62: Pacific | G62: https://www.siskiyous.edu | H62: https://www.siskiyous.edu/board/ | M62: Dr. Char Perlas | N62: 2022 | O62: N | P62: cperlas@siskiyous.edu | X62: (530) 938-5200 | Y62: TBD | AA62: College of the Siskiyous800 College Ave.Weed, CA 96094
A63: CC-062 | B63: Columbia College | C63: Community College District | D63: Yosemite Community College District | E63: California | F63: Pacific | G63: https://www.gocolumbia.edu | H63: https://www.yosemite.edu/trustees/index.html | I63: Dr. Lena Tran (I) | J63: (209) 575-6509 | K63: Office of the Chancellor P.O. BOX 4065 Modesto, CA 95352 | L63: tranl@yosemite.edu | M63: Chad Redwing | N63: 2025 | O63: Y | P63: redwingc@yosemite.edu | X63: 209-588-5115 | Y63: Jasmine Sedlmeyer | Z63: sedlmeyerj@yosemite.edu | AA63: Columbia College 11600 Columbia College Drive Sonora, CA 95730 | AC63: https://gocolumbia.edu/administration/research_planning/content/planning_documents/cc_strategic_plan_2022.pdf | AD63: 2022-2027
A64: CC-063 | B64: Compton College | C64: Community College | E64: California | F64: Pacific | G64: https://www.compton.edu | H64: https://www.compton.edu/district/board-of-trustees/index.aspx | M64: Dr. Keith Curry | N64: 2013 | O64: N | P64: kcurry@compton.edu | X64: (310) 900-1600 ext 2000 | Y64: Sylvia Barakat | Z64: sbarakat@compton.edu | AA64: 1111 E. Artesia Boulevard Compton, CA 90221 | AC64: https://www.compton.edu/about/masterplan/docs/Compton-College-2035.pdf | AD64: 2035
A65: CC-064 | B65: Contra Costa College | C65: Community College District | D65: Contra Costa Community College District | E65: California | F65: Pacific | G65: https://www.contracosta.edu | H65: https://www.4cd.edu/gb/index.html | I65: Mojdeh Mehdizadeh | J65: 925.229.6825 | K65: Office of the Chancellor Contra Costa Community College District 500 Court Street Martinez, CA 94553 | L65: mojdeh@4cd.edu | M65: Dr. Kimberly R. Rogers | N65: 2023 | O65: N | P65: krogers@contracosta.edu | X65: (510) 215-3806 | Y65: Jackie Ore | Z65: jore@contracosta.edu | AA65: Contra Costa College 2600 Mission Bell Drive San Pablo, CA 94806-3166 | AC65: https://www.4cd.edu/research/district-strategic-plan/index.html | AD65: 2025-2030
A66: CC-065 | B66: Copper Mountain College | C66: Community College | E66: California | F66: Pacific | G66: https://www.cmccd.edu | M66: Dr. Daren M. Otten | N66: 2019 | O66: N | P66: dotten@cmccd.edu | X66: 760-366-3791 ext. 5289 | Y66: Ariana Muñiz | Z66: amuniz@cmccd.edu | AA66: Superintendent/President Copper Mountain College 6162 Rotary Way Joshua Tree, CA 92252
A67: CC-066 | B67: Cosumnes River College | C67: Community College District | D67: Los Rios Community College District | E67: California | F67: Pacific | G67: https://crc.losrios.edu | H67: https://losrios.edu/about-los-rios/board-of-trustees | I67: Dr. Torence Powell (2026) | J67: (916) 568-3021 | K67: Los Rios Community College District1919 Spanos CourtSacramento, CA 95825-3981 | L67: powellt@losrios.edu | M67: Dr. Edward Bush | N67: 2015 | O67: N | P67: BushE@crc.losrios.edu | X67: (916) 691-7311 | Y67: Rachel C Larsen | Z67: LarsenR@crc.losrios.edu | AA67: 8401 Center Parkway Sacramento, CA 95823 | AC67: https://employees.crc.losrios.edu/institutional-equity-and-research-and-planning/planning/college-strategic-plan-area-goals-and-strategies
A68: CC-067 | B68: Crafton Hills College | D68: San Bernardino Community College District | E68: California | F68: Pacific | G68: https://www.craftonhills.edu | H68: https://sbccd.edu/about-sbccd/board-of-trustees/index.php | I68: Dr. Diana Z. Rodriguez | J68: (909) 388-6901 | K68: Office of the Chancellor 550 E. Hospitality Lane, Suite 200 San Bernardino, CA 92408 | L68: drodriguez@sbccd.edu | M68: Dr. Kevin Horan | N68: 2019 | O68: N | P68: khoran@craftonhills.edu | X68: 909) 389-3201 | Y68: Cyndie St. Jean | Z68: stjean@craftonhills.edu | AA68: Crafton Hills College11711 Sand Canyon RoadYucaipa, CA 92399 | AC68: https://www.craftonhills.edu/visitors-and-alumni/giving-to-chc/about-the-foundation/documents/strategic-plan.pdf | AD68: 2024-2029
A69: CC-068 | B69: Cuesta College | C69: Community College | E69: California | F69: Pacific | G69: https://www.cuesta.edu | H69: https://www.cuesta.edu/about/boardtrustees/index.html | M69: Dr. Jill Stearns | N69: 2018 | O69: N | P69: jill_stearns@cuesta.edu | X69: (805) 546-3118 | Y69: Cindy Dilbeck | Z69: cynthia_dilbeck@cuesta.edu | AA69: P.O. Box 8106 San Luis Obispo, CA 93403-8106
A70: CC-069 | B70: Cuyamaca College | C70: Community College District | D70: Grossmont-Cuyamaca Community College District | E70: California | F70: Pacific | G70: https://www.cuyamaca.edu | H70: https://www.gcccd.edu/governing-board/index.php | I70: Dr. Lynn Ceresino Neault | J70: (619) 644-7570 | K70: Grossmont-Cuyamaca Community College District 8800 Grossmont College Drive El Cajon, CA 92020 | L70: lynn.neault@gcccd.edu | M70: Jessica Robinson | N70: 2023 | O70: N | P70: jessica.robinson@gcccd.edu | X70: (619) 660-4221 | Y70: Valeri Wilson | Z70: valeri.wilson@gcccd.edu | AA70: 900 Rancho San Diego Parkway, El Cajon, CA 92019
A71: CC-070 | B71: Cypress College | C71: Community College District | D71: North Orange County Community College District | E71: California | F71: Pacific | G71: https://www.cypresscollege.edu | H71: https://www.nocccd.edu/board-trustees | I71: Dr. Byron D. Clift Breland | J71: (714) 808-4797 | K71: District Office, Chancellor 1830 W. Romneya Drive Anaheim, CA 92801-1819 | L71: bbreland@nocccd.edu | M71: Dr. Scott W. Thayer | N71: 2024 | O71: N | P71: sthayer@cypresscollege.edu | X71: (714) 484-7308 | Y71: Mercedes Milner | Z71: mmilner@cypresscollege.edu | AA71: Cypress College Office of the President (Complex, Office 328) 9200 Valley View Street Cypress, CA 90630
A72: CC-071 | B72: De Anza College | C72: Community College District | D72: Foothill-De Anza Community College District | E72: California | F72: Pacific | G72: https://www.deanza.edu | H72: https://www.fhda.edu/_about-us/_board/index.html | I72: Lee D. Lambert | J72: 650-949-6100 | K72: Foothill-De Anza Community College DistrictBuilding D700, Suite 25012345 El Monte RoadLos Altos Hills, CA 94022-4599 | L72: lambertlee@fhda.edu | M72: Dr. David Coon | N72: 2026 | O72: Y | P72: coondavid@deanza.edu | X72: (408) 864-8973 | Y72: Nathaly Aguilar | Z72: aguilarnathaly@deanza.edu | AA72: De Anza College Office of the President 21250 Stevens Creek Blvd. Cupertino, CA 95014
A73: CC-072 | B73: Diablo Valley College | C73: Community College District | D73: Contra Costa Community College District | E73: California | F73: Pacific | G73: https://www.dvc.edu | H73: https://www.4cd.edu/gb/index.html | I73: Mojdeh Mehdizadeh | J73: 925.229.6825 | K73: Office of the Chancellor Contra Costa Community College District 500 Court Street Martinez, CA 94553 | L73: mojdeh@4cd.edu | M73: Dr. Monica Chahal | N73: 2025 | O73: N | P73: mchahal@dvc.edu | X73: (925) 969-2001 | Y73: Marta Gillen | Z73: 9200 Valley View Street | AA73: President Diablo Valley College 321 Golf Club Road Pleasant Hill, CA 94523 | AC73: https://www.4cd.edu/research/district-strategic-plan/index.html | AD73: 2025-2030
A74: CC-073 | B74: East Los Angeles College | C74: Community College District | D74: Los Angeles Community College District | E74: California | F74: Pacific | G74: https://www.elac.edu | H74: https://www.laccd.edu/board | I74: Dr. Alberto J. Román | J74: (213) 891-2000 ext.2173 | K74: 770 Wilshire Blvd, Los Angeles, CA 90017 | L74: romanaj@email.laccd.edu | M74: Dr. Monte E. Perez | N74: 2024 | O74: N | P74: perezme@elac.edu | X74: (323) 265-8650 | AA74: 1301 Avenida Cesar Chavez, Monterey Park, CA 91754-6099
A75: CC-074 | B75: El Camino College | C75: Community College | E75: California | F75: Pacific | G75: https://www.elcamino.edu | H75: https://www.elcamino.edu/leadership/trustees/ | M75: Dr. Brenda Thames | N75: 2021 | O75: N | P75: bthames@elcamino.edu | X75: (310) 660-3593, Ext. 3111 | Y75: Rose Sandro | Z75: rsandro@elcamino.edu | AA75: 16007 Crenshaw Boulevard, Torrance, CA 90506
A76: CC-075 | B76: Evergreen Valley College | C76: Community College District | D76: San José-Evergreen Community College District | E76: California | F76: Pacific | G76: https://www.evc.edu | H76: https://sjeccd.edu/discover-sjeccd/board-of-trustees | I76: Dr. Beatriz Chaidez | J76: 408-270-6402 | K76: District Office 40 S. Market Street San José, CA 95113 | L76: beatriz.chaidez@sjeccd.edu | M76: Dr. Vinicio J. López | N76: 2024 | O76: N | P76: Vinicio.López@evc.edu | X76: (408) 270-6471 | Y76: Penny L. Garibay | Z76: Penny.Garibay@evc.edu | AA76: Evergreen Valley CollegeAttn: Office of the President3095 Yerba Buena RoadSan Jose, CA 95135
A77: CC-076 | B77: Feather River College | E77: California | F77: Pacific | G77: https://www.frc.edu | H77: https://www.frc.edu/administration/board-of-trustees | M77: Dr. Kevin Trutna | N77: 2012 | O77: N | P77: KTrutna@frc.edu | X77: (530) 283-0202, Ext. 232 | Y77: Cheryl Kolb | Z77: ckolb@frc.edu | AA77: Feather River College570 Golden Eagle Avenue Quincy, CA 95971
A78: CC-077 | B78: Folsom Lake College | C78: Community College District | D78: Los Rios Community College District | E78: California | F78: Pacific | G78: https://flc.losrios.edu | H78: https://losrios.edu/about-los-rios/board-of-trustees | I78: Dr. Torence Powell (2026) | J78: (916) 568-3021 | K78: Los Rios Community College District1919 Spanos CourtSacramento, CA 95825-3981 | L78: powellt@losrios.edu | M78: Dr. Art Pimentel | N78: 2023 | O78: N | P78: Pimentel@flc.losrios.edu | X78: (916) 608-6570 | Y78: Karla R. Lozano | Z78: LozanoK@flc.losrios.edu | AA78: Folsom Lake College 10 College Parkway Folsom, CA 95630-6798 | AC78: https://flc.losrios.edu/flc/shared/doc/about-us/College-Strategic-Plan.pdf | AD78: 2025-2030
A79: CC-078 | B79: Foothill College | C79: Community College District | D79: Foothill-De Anza Community College District | E79: California | F79: Pacific | G79: https://foothill.edu | H79: https://www.fhda.edu/_about-us/_board/index.html | I79: Lee D. Lambert | J79: 650-949-6100 | K79: Foothill-De Anza Community College DistrictBuilding D700, Suite 25012345 El Monte RoadLos Altos Hills, CA 94022-4599 | L79: lambertlee@fhda.edu | M79: Dr. Kristina Whalen | N79: 2023 | O79: N | P79: whalenkristina@fhda.edu | X79: (650) 949-7200 | Y79: Antoinette Chavez
A80: CC-079 | B80: Fresno City College | D80: State Center Community College District | E80: California | F80: Pacific | G80: https://www.fresnocitycollege.edu | H80: https://www.scccd.edu/about/board-of-trustees/index.html | I80: Dr. Carole Goldsmith | J80: (559) 243-7100 ext 7102 | K80: Chancellor's Office State Center Community College District1171 Fulton Street Fresno, CA 93721 | L80: RETIRING - SEARCH IN PROGRESS | M80: Denise Whisenhunt | N80: 2025 | O80: N | P80: denise.whisenhunt@fresnocitycollege.edu | X80: 559.489.2212 | Y80: Laura Choi | Z80: laura.choi@fresnocitycollege.edu | AP80: Denise Whisenhunt, J.D. is an educational administrator who serves as the 13th President of Fresno City College. She is the first African American woman to lead the institution, which holds distinction as California’s first community college
A81: CC-080 | B81: Fullerton College | C81: Community College District | D81: North Orange County Community College District | E81: California | F81: Pacific | G81: https://www.fullcoll.edu | H81: https://www.nocccd.edu/board-trustees | I81: Dr. Byron D. Clift Breland | J81: (714) 808-4797 | K81: District Office, Chancellor 1830 W. Romneya Drive Anaheim, CA 92801-1819 | L81: bbreland@nocccd.edu | M81: Dr. Cynthia Olivo | N81: 2023 | O81: N | P81: colivo@fullcoll.edu | X81: (714) 992-7001 | Y81: Jean E. Foster | Z81: jfoster@fullcoll.edu | AA81: Office of the President 321 E. Chapman Avenue Fullerton, CA 92832
A82: CC-081 | B82: Gavilan College | C82: Community College | E82: California | F82: Pacific | G82: https://www.gavilan.edu | H82: https://www.gavilan.edu/administration/board/index.php | M82: Dr. Pedro Avila | N82: 2022 | O82: N | P82: pedroavila@gavilan.edu | X82: 408-848-4712 | Y82: Michelle Jones | Z82: mjones@gavilan.edu | AA82: Superintendent/President Gavilan College 5055 Santa Teresa Boulevard Gilroy, CA 95020
A83: CC-082 | B83: Glendale Community College | C83: Community College | E83: California | F83: Pacific | G83: https://www.glendale.edu | H83: https://www.glendale.edu/about-gcc/board-of-trustees/index.html | M83: Dr. Ryan Cornner | N83: 2022 | O83: N | P83: rcornner@glendale.edu | X83: (623) 845-3010 | Y83: Debra Kallas | Z83: myemail@glendale.edu | AA83: Superintendent/PresidentGlendale Community College1500 North Verdugo RoadGlendale, CA 91208
A84: CC-083 | B84: Golden West College | C84: Community College District | D84: Coast Community College District | E84: California | F84: Pacific | G84: https://www.goldenwestcollege.edu | H84: https://www.cccd.edu/boardoftrustees/index.html | I84: Dr. Whitney Yamamura | J84: (714)438-4732 | K84: 1370 Adams Avenue Costa Mesa, CA 92626 | L84: wyamamura@cccd.edu | M84: Meridith Randall | N84: 2023 | O84: N | P84: mrandall12@gwc.cccd.edu | X84: (714) 895-8178 | Y84: Diana Retes | Z84: dretes@gwc.cccd.edu | AA84: 15744 Goldenwest Street, Huntington Beach, CA 92647 | AC84: https://www.goldenwestcollege.edu/Links/pdf/research/gwc_strategic_plan_20025_2029.pdf | AD84: 2025-2029
A85: CC-084 | B85: Grossmont College | C85: Community College District | D85: Grossmont-Cuyamaca Community College District | E85: California | F85: Pacific | G85: https://www.grossmont.edu | H85: https://www.gcccd.edu/governing-board/index.php | I85: Dr. Lynn Ceresino Neault | J85: (619) 644-7570 | K85: Grossmont-Cuyamaca Community College District 8800 Grossmont College Drive El Cajon, CA 92020 | L85: lynn.neault@gcccd.edu | M85: Dr. Pamela Luster | N85: 2025 | O85: Y | P85: pamela.luster@gcccd.edu | X85: (619) 644-7570 | Y85: Bernadette Black | Z85: Bernadette.Black@gcccd.edu | AA85: Office of the President, 8800 Grossmont College Drive, El Cajon, CA 92020
A86: CC-085 | B86: Hartnell College | C86: Community College | E86: California | F86: Pacific | G86: https://www.hartnell.edu | H86: https://www.hartnell.edu/about/hccdgb/ | M86: Michael Gutierrez | N86: 2022 | O86: N | P86: mjgutierrez@hartnell.edu | X86: 831-755-6900 | Y86: Lucille Serrano | Z86: lserrano@hartnell.edu | AA86: Superintendent/PresidentHartnell College411 Central Avenue
A87: CC-086 | B87: Imperial Valley College | C87: Community College | E87: California | F87: Pacific | G87: https://www.imperial.edu | H87: https://imperial.community.diligentoneplatform.com/Portal/ | M87: TBD - CURRENT PRESIDENT IS NOW MIRA COSTA PRESIDENT | N87: 2022 | O87: N
A88: CC-087 | B88: Irvine Valley College | C88: Community College District | D88: South Orange County Community College District | E88: California | F88: Pacific | G88: https://www.ivc.edu | H88: https://www.socccd.edu/board-trustees | I88: Dr. Julianna M. Barnes | J88: 949-582-4840 | K88: South Orange County Community College DistrictOffice of the Chancellor, Third Floor, HS BuildingSaddleback College28000 Marguerite ParkwayMission Viejo, CA 92692 | L88: jbarnes@soccd.edu | M88: Dr. John C. Hernandez | N88: 2020 | O88: N | P88: johnhernandez@ivc.edu | X88: (949) 451-5100 | AP88: May need to double check pres email
A89: CC-088 | B89: Lake Tahoe Community College | C89: Community College | E89: California | F89: Pacific | G89: https://www.ltcc.edu | H89: https://www.ltcc.edu/about/board-of-trustees/index.php | M89: Jeff DeFranco | AP89: president announed resignation in March 2026
A90: CC-089 | B90: Laney College | C90: Community College District | D90: Peralta Community College District | E90: California | F90: Pacific | G90: https://www.laney.edu | H90: https://www.peralta.edu/boardoftrustees | I90: Dr. Tammeil Gilkerson | J90: 510/466-7322 | K90: Peralta Community College District 333 East Eighth Street Oakland, CA 94606 | L90: tgilkerson@peralta.edu | M90: Dr. Becky Opsata | N90: 2025 | O90: Y | P90: ropsata@peralta.edu | X90: (510) 464-3219 | Y90: Judy Mei | Z90: jmei@peralta.edu | AA90: Laney College Office of the President 900 Fallon Street Oakland, CA 94607
A91: CC-090 | B91: Las Positas College | E91: California | F91: Pacific | G91: https://www.laspositascollege.edu | H91: https://www.clpccd.org/bot/index.php | I91: Ronald P. Gerhard | J91: (925) 485-5206 | K91: Chabot-Las Positas Community College District7600 Dublin Blvd, 3rd FloorDublin, CA 94568 | L91: rgerhard@clpccd.org | M91: Dr. Dyrell Foster | N91: 2020 | O91: N | P91: dfoster@laspositascollege.edu | X91: 925.424.1001 | Y91: Angelica Cazarez | Z91: acazarez@laspositascollege.edu | AA91: 3000 Campus Hill Drive Room 1680 Livermore, CA 94551
A92: CC-091 | B92: Lassen College | C92: Community College | E92: California | F92: Pacific | G92: https://www.lassencollege.edu | H92: https://www.lassencollege.edu/about-lcc/board-of-trustees/ | M92: Carie Camacho | N92: 2025 | O92: N | P92: ccamacho@lassencollege.edu | X92: (530) 251-8820 | Y92: Chauncine Stewart | Z92: stewarcr@lasc.edu | AA92: Superintendent/President Lassen Community CollegeP.O. Box 3000Susanville, CA 96130
A93: CC-092 | B93: Lemoore College | C93: Community College District | D93: West Hills Community College District | E93: California | F93: Pacific | G93: https://www.westhillscollege.com/lemoore | H93: https://westhillscollege.com/district/administration/board-of-trustees/ | I93: Dr. Robert Pimentel | J93: (559) 934-2131 | K93: West Hills Community College District 275 Phelps Ave Coalinga, CA 93210 | L93: robertpimentel@whccd.edu | M93: James Preston | N93: 2022 | O93: N | P93: jamespreston@whccd.edu | X93: (559) 925-3146 | AA93: President Lemoore College 555 College Avenue Lemoore, CA 93245 | AC93: https://issuu.com/westhillsmagazine/docs/64506728_whcl_strategic_plan_2021-2026?mode=window | AD93: 2021-2026
A94: CC-093 | B94: Long Beach City College | E94: California | F94: Pacific | G94: https://www.lbcc.edu | H94: https://www.lbcc.edu/board-trustees | M94: Dr. Mike Muñoz | N94: 2021 | O94: N | P94: mmunoz@lbcc.edu | X94: (562) 938-4121 | Y94: Lauren Zale | Z94: lzale@lbcc.edu | AA94: Office of the Superintendent-President, Long Beach City College, 4901 E. Carson Street, Long Beach, CA 90808
A95: CC-094 | B95: Los Angeles City College | D95: Los Angeles Community College District | E95: California | F95: Pacific | G95: https://www.lacitycollege.edu | H95: https://www.laccd.edu/board | I95: Dr. Alberto J. Román | J95: (213) 891-2000 ext.2173 | K95: 770 Wilshire Blvd, Los Angeles, CA 90017 | L95: romanaj@email.laccd.edu | M95: Dr. Amanuel Gebru | N95: 2023 | O95: N | P95: gebrua@lacitycollege.edu | X95: (323) 953-4000 Ext. 2242 | Y95: Angela Miller | AA95: 855 N. Vermont Avenue, Los Angeles California 90029
A96: CC-095 | B96: Los Angeles Harbor College | D96: Los Angeles Community College District | E96: California | F96: Pacific | G96: https://www.lahc.edu | H96: https://www.laccd.edu/board | I96: Dr. Alberto J. Román | J96: (213) 891-2000 ext.2173 | K96: 770 Wilshire Blvd, Los Angeles, CA 90017 | L96: romanaj@email.laccd.edu | M96: Dr. Luis Dorado | O96: N | P96: doradol@lahc.edu | X96: (310) 233-4010 | Y96: Aracely Martinez | Z96: MARTINA3@LAHC.EDU | AA96: Attn: Office of the President (SSA 216)1111 Figueroa PlaceWilmington, CA 90744
A97: CC-096 | B97: Los Angeles Mission College | D97: Los Angeles Community College District | E97: California | F97: Pacific | G97: https://www.lamission.edu | H97: https://www.laccd.edu/board | I97: Dr. Alberto J. Román | J97: (213) 891-2000 ext.2173 | K97: 770 Wilshire Blvd, Los Angeles, CA 90017 | L97: romanaj@email.laccd.edu | M97: Dr. Armida Ornelas | N97: 2021 | O97: N | P97: ornelaao@lamission.edu | X97: (818) 364-7795 | Y97: Oliva Ayala | Z97: sancheo@lamission.edu | AA97: Los Angeles Mission College Office of the President 13356 Eldridge AvenueSylmar, CA 91342
A98: CC-097 | B98: Los Angeles Pierce College | D98: Los Angeles Community College District | E98: California | F98: Pacific | G98: https://www.piercecollege.edu | H98: https://www.laccd.edu/board | I98: Dr. Alberto J. Román | J98: (213) 891-2000 ext.2173 | K98: 770 Wilshire Blvd, Los Angeles, CA 90017 | L98: romanaj@email.laccd.edu | M98: Aracely Aguiar | N98: 2024 | O98: N | P98: aguiara@piercecollege.edu | X98: 3102874238 ext 4238 | Y98: Malina Koani | Z98: koanimk@piercecollege.edu | AA98: LA Pierce College c/o Office of the President, 6201 Winnetka Ave, Woodland Hills, CA 91371
A99: CC-098 | B99: Los Angeles Southwest College | D99: Los Angeles Community College District | E99: California | F99: Pacific | G99: https://www.lasc.edu | H99: https://www.laccd.edu/board | I99: Dr. Alberto J. Román | J99: (213) 891-2000 ext.2173 | K99: 770 Wilshire Blvd, Los Angeles, CA 90017 | L99: romanaj@email.laccd.edu | M99: Dr. Anthony Culpepper | N99: 2023 | O99: N | P99: culpepaj@lasc.edu | X99: (323) 241-5276 | AA99: Los Angeles Southwest College1600 W. Imperial HighwayLos Angeles, CA 90047-4810
A100: CC-099 | B100: Los Angeles Trade-Technical College | D100: Los Angeles Community College District | E100: California | F100: Pacific | G100: https://www.lattc.edu | H100: https://www.laccd.edu/board | I100: Dr. Alberto J. Román | J100: (213) 891-2000 ext.2173 | K100: 770 Wilshire Blvd, Los Angeles, CA 90017 | L100: romanaj@email.laccd.edu | M100: Dr. Alfred McQuarters | N100: 2023 | O100: N | P100: mcquarad@lattc.edu | X100: (213) 763-7052 | AA100: 400 W Washington Blvd, Los Angeles, CA 90015
...

Sheet College Associations
A1: Org ID | B1: Organization | C1: Institution Type | D1: State | E1: Region | F1: Website | G1: Board Page | H1: President/CEO | I1: Interim (Y/N) | J1: Primary Email | K1: Board Chair | L1: Term Begin (C) | M1: Term End (C) | N1: Board Vice Chair | O1: Term Begin (VC) | P1: Term End (VC) | Q1: Board email | R1: Primary Phone | S1: Executive Assistant/Office Manager | T1: Executive Assistant Email | U1: Mailing Address | V1: Strategic Priorities | W1: Strategic Plan | X1: Strategic Plan Years | Y1: Current Initiatives | Z1: Accreditation Cycle | AA1: Recent News/Governance Notes | AB1: Date Identified | AC1: Last Contact | AD1: Next Follow-up | AE1: Relationship Status | AF1: Priority | AG1: Fit Score | AH1: Packet Sent? | AI1: Notes | AJ1: Last Verified Date
A2: AA-001 | B2: Washington Association of Community and Technical Colleges (WACTC) | C2: Association | D2: Washington | E2: Pacific Northwest | F2: https://www.sbctc.edu/colleges-staff/commissions-councils/wactc/default.aspx | G2: https://www.sbctc.edu/colleges-staff/commissions-councils/wactc/membership.aspx | H2: Nate Humphrey | I2: N | J2: nhumphrey@sbctc.edu | R2: 360-704-4355 | S2: Nanette Angel | T2: nangel@sbctc.edu | U2: SBCTC PO Box 42495 Olympia, WA 98504-2495 | W2: https://www.sbctc.edu/about/agency/initiatives-projects/strategic-plan/default.aspx | X2: 2020-2030
A3: AA-002 | B3: Community College League of California | C3: Association | D3: California | E3: Pacific Northwest | F3: https://www.ccleague.org/?utm_source=chatgpt.com | G3: https://www.ccleague.org/about-us/california-community-college-trustees-ccct/ | H3: Larry Galizio | I3: N | J3: galizio@ccleague.org | R3: 9162455032 | S3: Agnes Lupa | T3: agnes@ccleague.org | U3: 2017 O Street, Sacramento CA 95811-5211
A4: AA-003 | B4: Academic Senate for California Community Colleges
A5: AA-004
A6: AA-005
A7: AA-006
A8: AA-007
A9: AA-008
A10: AA-009
A11: AA-010
A12: AA-011
A13: AA-012
A14: AA-013
A15: AA-014
A16: AA-015
... A29: AA-028
A246: ORG-245 | B246: Washington Association of Community and Technical Colleges (WACTC) | C246: Association | D246: Washington | E246: Pacific Northwest | F246: https://www.sbctc.edu/colleges-staff/commissions-councils/wactc/default.aspx | H246: Nate Humphrey | I246: N | R246: 360-704-4355 | S246: Nanette Angel | T246: nangel@sbctc.edu | U246: SBCTC PO Box 42495 Olympia, WA 98504-2495 | AI246: Contact Information for Board of Presidents

Sheet Contacts
A1: Contact ID | B1: Organization | C1: First Name | D1: Last Name | E1: Title | F1: Role Type | G1: Email | H1: Phone | I1: LinkedIn | J1: Preferred Contact | K1: Influence Level | L1: Relationship Strength | M1: Last Contact | N1: Next Follow-up | O1: Notes
A2: CON-001 | B2: Example Community College | C2: First | D2: Last | E2: Board Chair | F2: Board Chair | G2: chair@example.edu | H2: 555-555-0101 | I2: https://linkedin.com/in/example | J2: Email | K2: High | L2: New | M2: 46205 | N2: 46212 | O2: Sample contact.
A3: CON-002
A4: CON-003
A5: CON-004
A6: CON-005
A7: CON-006
A8: CON-007
A9: CON-008
A10: CON-009
A11: CON-010
A12: CON-011
A13: CON-012
A14: CON-013
... A101: CON-100

Sheet Opportunities
A1: Opportunity ID | B1: Opportunity Name | C1: Organization | D1: Service Type | E1: Estimated Value | F1: Probability % | G1: Weighted Pipeline | H1: Stage | I1: Expected Close | J1: Lead Source | K1: Priority | L1: Last Activity | M1: Next Follow-up | N1: Days Since Last Activity | O1: Status | P1: Notes
A2: OPP-001 | B2: Board Alignment & Strategy Retreat | C2: Example Community College | D2: Board Retreat | E2: 15000 | F2: 0.6 | G2: =IFERROR(E2*F2,0) -> 9000 | H2: Research Complete | I2: 46249 | J2: Direct Outreach | K2: High | L2: 46205 | M2: 46212 | N2: =IF(L2="","",TODAY()-L2) -> 4 | O2: Open | P2: Sample opportunity.
A3: OPP-002
A4: OPP-003
A5: OPP-004
A6: OPP-005
A7: OPP-006
A8: OPP-007
A9: OPP-008
A10: OPP-009
A11: OPP-010
A12: OPP-011
A13: OPP-012
A14: OPP-013
... A100: OPP-099

Sheet Outreach Activities
A1: Activity ID | B1: Date | C1: Organization | D1: Contact | E1: Activity Type | F1: Channel | G1: Summary | H1: Outcome | I1: Next Action | J1: Next Follow-up | K1: Completed? | L1: Related Opportunity
A2: ACT-001 | B2: 46205 | C2: Example Community College | D2: First Last | E2: Mailed Packet | F2: Mail | G2: Initial Board Chair Executive Packet mailed. | H2: Packet sent | I2: Email follow-up | J2: 46212 | K2: No | L2: Board Alignment & Strategy Retreat
A3: ACT-002
A4: ACT-003
A5: ACT-004
A6: ACT-005
A7: ACT-006
A8: ACT-007
A9: ACT-008
A10: ACT-009
A11: ACT-010
A12: ACT-011
A13: ACT-012
A14: ACT-013
... A100: ACT-099

Sheet Proposals
A1: Proposal ID | B1: Organization | C1: Opportunity | D1: Date Sent | E1: Services Offered | F1: Amount | G1: Status | H1: Decision Date | I1: Days Pending | J1: Follow-up Date | K1: Notes
A2: PROP-001 | B2: Example Community College | C2: Board Alignment & Strategy Retreat | D2: 46218 | E2: Full-day retreat + readiness assessment | F2: 15000 | G2: Drafting | I2: =IF(D2="","",IF(H2="",TODAY()-D2,H2-D2)) -> -9 | J2: 46225 | K2: Sample proposal tracker.
A3: PROP-002
A4: PROP-003
A5: PROP-004
A6: PROP-005
A7: PROP-006
A8: PROP-007
A9: PROP-008
A10: PROP-009
A11: PROP-010
A12: PROP-011
A13: PROP-012
A14: PROP-013
... A100: PROP-099

Sheet Engagements
A1: Engagement ID | B1: Organization | C1: Engagement Type | D1: Start Date | E1: End Date | F1: Status | G1: Travel Required? | H1: Lead Consultant | I1: Contract Value | J1: Follow-up Service Opportunity | K1: Notes
A2: ENG-001 | B2: Example Community College | C2: Board Retreat | D2: 46277 | E2: 46277 | F2: Scheduled | G2: Yes | H2: Dr. Adrien L. Bennings | I2: 15000 | J2: Executive coaching follow-up | K2: Sample engagement.
A3: ENG-002
A4: ENG-003
A5: ENG-004
A6: ENG-005
A7: ENG-006
A8: ENG-007
A9: ENG-008
A10: ENG-009
A11: ENG-010
A12: ENG-011
A13: ENG-012
A14: ENG-013
... A100: ENG-099

Sheet Revenue
A1: Revenue ID | B1: Organization | C1: Opportunity | D1: Estimated Revenue | E1: Contracted Revenue | F1: Invoice Date | G1: Payment Received | H1: Payment Status | I1: Travel Reimbursed | J1: Profitability Notes
A2: REV-001 | B2: Example Community College | C2: Board Alignment & Strategy Retreat | D2: 15000 | E2: 15000 | F2: 46266 | G2: 0 | H2: Invoice Sent | I2: 0 | J2: Sample revenue tracker.
A3: REV-002
A4: REV-003
A5: REV-004
A6: REV-005
A7: REV-006
A8: REV-007
A9: REV-008
A10: REV-009
A11: REV-010
A12: REV-011
A13: REV-012
A14: REV-013
... A100: REV-099

Sheet Speaking
A1: Event ID | B1: Event | C1: Organization/Host | D1: Date | E1: Location | F1: Audience | G1: Proposal Status | H1: Fee | I1: Attendees | J1: Leads Generated | K1: Follow-up Date | L1: Notes
A2: SPK-001 | B2: State Board Conference | C2: Example Association | D2: 46310 | E2: TBD | F2: Board chairs and presidents | G2: Planning | H2: 7500 | I2: 150 | J2: 10 | K2: 46315 | L2: Sample speaking opportunity.
A3: SPK-002
A4: SPK-003
A5: SPK-004
A6: SPK-005
A7: SPK-006
A8: SPK-007
A9: SPK-008
A10: SPK-009
A11: SPK-010
A12: SPK-011
A13: SPK-012
A14: SPK-013
... A100: SPK-099

Sheet Referrals
A1: Referral ID | B1: Referral Source | C1: Source Type | D1: Organization Referred | E1: Contact | F1: Date | G1: Outcome | H1: Estimated Value | I1: Notes
A2: REF-001 | B2: Former President Name | C2: Former President | D2: Example Community College | E2: President Name | F2: 46205 | G2: Introduced | H2: 15000 | I2: Sample referral.
A3: REF-002
A4: REF-003
A5: REF-004
A6: REF-005
A7: REF-006
A8: REF-007
A9: REF-008
A10: REF-009
A11: REF-010
A12: REF-011
A13: REF-012
A14: REF-013
... A100: REF-099

Sheet Content Marketing
A1: Content ID | B1: Content Title | C1: Type | D1: Publish Date | E1: Channel | F1: CTA | G1: Leads Generated | H1: Inquiries | I1: Notes
A2: CNT-001 | B2: Five Signs Your Board Retreat Needs More Than an Agenda | C2: Article | D2: 46205 | E2: LinkedIn | F2: Download readiness assessment | G2: 5 | H2: 2 | I2: Sample content marketing record.
A3: CNT-002
A4: CNT-003
A5: CNT-004
A6: CNT-005
A7: CNT-006
A8: CNT-007
A9: CNT-008
A10: CNT-009
A11: CNT-010
A12: CNT-011
A13: CNT-012
A14: CNT-013
... A100: CNT-099

Sheet Lists
A1: Relationship Status | B1: Pipeline Stage | C1: District | D1: Service Type | E1: Activity Type | F1: Priority | G1: Institution Type | H1: Region | I1: Proposal Status | J1: Engagement Status | K1: Payment Status | L1: Yes/No | M1: Role Type | N1: Influence Level | O1: Relationship Strength
A2: Cold Prospect | B2: Prospect Identified | C2: Coast Community College District | D2: Board Retreat | E2: Mailed Packet | F2: High | G2: Community College | H2: Pacific Northwest | I2: Drafting | J2: Not Started | K2: Not Invoiced | L2: Yes | M2: President/CEO | N2: High | O2: New
A3: Warm Prospect | B3: Research Complete | C3: Contra Costa Community College District | D3: Governance Assessment | E3: Email | F3: Medium | G3: Community College District | H3: Pacific | I3: Sent | J3: Scheduled | K3: Invoice Sent | L3: No | M3: Board Chair | N3: Medium | O3: Developing
A4: Packet Sent | B4: Executive Packet Sent | C4: Foothill-De Anza Community College District | D4: Strategic Planning | E4: LinkedIn Connection | F4: Low | G4: State System | H4: Southwest | I4: Pending Decision | J4: In Progress | K4: Partial Payment | M4: Board Vice Chair | N4: Low | O4: Warm
A5: Follow-up Needed | B5: Email Follow-up | C5: Grossmont-Cuyamaca Community College District | D5: Executive Coaching | E5: Phone Call | G5: University | H5: Mountain West | I5: Revision Requested | J5: Completed | K5: Paid | M5: Trustee | O5: Strong
A6: Discovery Scheduled | B6: Phone Follow-up | C6: Kern Community College District | D6: Leadership Development | E6: Discovery Meeting | G6: Foundation | H6: Great Plains | I6: Accepted | J6: Follow-up Pending | K6: Overdue | M6: Board Coordinator | O6: Strategic
A7: Active Opportunity | B7: Discovery Call Scheduled | C7: Los Angeles Community College District | D7: Keynote Speaking | E7: Conference Interaction | G7: Association | H7: Midwest | I7: Declined | J7: Renewed | M7: Executive Assistant
A8: Client | B8: Discovery Call Completed | C8: Los Rios Community College District | D8: Workshop | E8: Proposal Follow-up | G8: Nonprofit | H8: West | I8: Paused | M8: Foundation CEO
A9: Past Client | B9: Proposal Sent | C9: North Orange County Community College District | D9: Annual Advisory | E9: Thank You Note | G9: Other | H9: South | M9: Cabinet Executive
A10: Dormant | B10: Negotiation | C10: Peralta Community College District | D10: Fractional Executive Advisory | E10: Referral Follow-up | H10: Southeast | M10: Referral Partner
A11: Do Not Contact | B11: Contract Signed | C11: Rancho Santiago Community College District | D11: Readiness Assessment | E11: Newsletter Touch | H11: Mid-Atlantic | M11: Other
B12: Retreat/Engagement Scheduled | C12: Riverside Community College District | H12: Northeast
B13: Engagement Complete | C13: San Bernardino Community College District | H13: National
B14: Follow-up Services | C14: San Diego Community College District | H14: International
B15: Annual Advisory Relationship | C15: San José-Evergreen Community College District
B16: Closed Won | C16: San Mateo County Community College District
B17: Closed Lost | C17: South Orange County Community College District
C18: State Center Community College District
C19: Ventura County Community College District
C20: West Hills Community College District
C21: West Valley-Mission Community College District
C22: Yosemite Community College District
C23: Yuba Community College District

Sheet How to Use
A1: How to Use the Executive Opportunity Pipeline
A3: Step | B3: Action
A4: 1 | B4: Enter each institution in Organizations first.
A5: 2 | B5: Add presidents, board chairs, coordinators, and assistants in Contacts.
A6: 3 | B6: Create an Opportunity for each potential service: board retreat, strategic planning, governance assessment, executive coaching, speaking, or advisory.
A7: 4 | B7: Log every mailed packet, email, LinkedIn touch, call, and meeting in Outreach Activities.
A8: 5 | B8: Use Next Follow-up dates to drive your weekly business development rhythm.
A9: 6 | B9: Track proposal status and amount in Proposals.
A10: 7 | B10: Once contracted, move the work into Engagements and Revenue.
A11: 8 | B11: Use the Dashboard weekly to review pipeline, follow-ups, proposals, and weighted revenue.
A12: Design Note | B12: This system is intentionally framed as executive relationship management rather than a generic sales CRM.
